framedwindow/__init__.py
framedwindow/framedwindow.py
framedwindow/wrappers.py
framedwindow-0.1.2.dist-info/METADATA
framedwindow-0.1.2.dist-info/WHEEL
framedwindow-0.1.2.dist-info/top_level.txt
framedwindow-0.1.2.dist-info/RECORD
