Metadata-Version: 2.1
Name: framedwindow
Version: 0.1.2
Summary: FramedWindow: simple wrappers for curese operations.
Home-page: http://vixal.net
Author: James M
Author-email: james.mattison7@gmail.com
License: UNKNOWN
Platform: UNKNOWN
Classifier: Programming Language :: Python :: 3
Classifier: License :: OSI Approved :: MIT License
Classifier: Operating System :: OS Independent
